README.md
setup.cfg
setup.py
SeqNN/SeqNN.py
SeqNN/SeqNNpp.lib
SeqNN/__init__.py
SeqNN.egg-info/PKG-INFO
SeqNN.egg-info/SOURCES.txt
SeqNN.egg-info/dependency_links.txt
SeqNN.egg-info/top_level.txt