Metadata-Version: 2.1
Name: SeqNN
Version: 0.0.3
Summary: A sequential neural network python extension
Home-page: https://github.com/BrettCleary/SeqNN
Author: Brett Cleary
Author-email: your.email@domain.com
License: MIT
Keywords: neural,network,sequential
Platform: UNKNOWN
Classifier: Development Status :: 3 - Alpha
Classifier: Intended Audience :: Developers
Classifier: Topic :: Software Development :: Build Tools
Classifier: License :: OSI Approved :: MIT License
Classifier: Programming Language :: Python :: 3
Classifier: Programming Language :: Python :: 3.4
Classifier: Programming Language :: Python :: 3.5
Classifier: Programming Language :: Python :: 3.6
